request_network/__init__.py
request_network/api.py
request_network/artifact_manager.py
request_network/constants.py
request_network/currencies.py
request_network/exceptions.py
request_network/signers.py
request_network/types.py
request_network/utils.py
request_network/artifacts/LICENSE
request_network/artifacts/README.md
request_network/artifacts/artifacts.json
request_network/artifacts/index.js
request_network/artifacts/package-lock.json
request_network/artifacts/package.json
request_network/artifacts/RequestBitcoinNodesValidation/RequestBitcoinNodesValidation-0.2.1-prod.json
request_network/artifacts/RequestBitcoinNodesValidation/RequestBitcoinNodesValidation-0.2.5-test.json
request_network/artifacts/RequestCore/RequestCore-0.0.5-prod.json
request_network/artifacts/RequestCore/RequestCore-0.0.5-test.json
request_network/artifacts/RequestERC20/RequestERC20-0.2.2-bat-main.json
request_network/artifacts/RequestERC20/RequestERC20-0.2.2-bnb-main.json
request_network/artifacts/RequestERC20/RequestERC20-0.2.2-centralbank-rinkeby.json
request_network/artifacts/RequestERC20/RequestERC20-0.2.2-dai-main.json
request_network/artifacts/RequestERC20/RequestERC20-0.2.2-dgx-main.json
request_network/artifacts/RequestERC20/RequestERC20-0.2.2-kin-main.json
request_network/artifacts/RequestERC20/RequestERC20-0.2.2-knc-main.json
request_network/artifacts/RequestERC20/RequestERC20-0.2.2-link-main.json
request_network/artifacts/RequestERC20/RequestERC20-0.2.2-omg-main.json
request_network/artifacts/RequestERC20/RequestERC20-0.2.2-req-main.json
request_network/artifacts/RequestERC20/RequestERC20-0.2.2-test-test.json
request_network/artifacts/RequestERC20/RequestERC20-0.2.2-zrx-main.json
request_network/artifacts/RequestEthereum/RequestEthereum-0.0.5-prod.json
request_network/artifacts/RequestEthereum/RequestEthereum-0.0.5-test.json
request_network/scripts/__init__.py
request_network/scripts/create_qr_code.py
request_network/services/ERC20.py
request_network/services/__init__.py
request_network-0.0.10.dist-info/LICENSE
request_network-0.0.10.dist-info/METADATA
request_network-0.0.10.dist-info/WHEEL
request_network-0.0.10.dist-info/entry_points.txt
request_network-0.0.10.dist-info/top_level.txt
request_network-0.0.10.dist-info/RECORD
