Metadata-Version: 2.1
Name: request-network
Version: 0.0.10
Summary: Python library for Request Network
Home-page: https://github.com/mikery/python-request-network
Author: Mike Ryan
Author-email: mike@backtothelab.io
License: UNKNOWN
Platform: UNKNOWN
Classifier: Development Status :: 2 - Pre-Alpha
Classifier: Programming Language :: Python :: 3
Classifier: Intended Audience :: Developers
Classifier: Natural Language :: English
Classifier: License :: OSI Approved :: MIT License
Classifier: Operating System :: OS Independent
Requires-Dist: web3 (==4.4.1)
Requires-Dist: PyQRCode (==1.2.1)
Requires-Dist: pypng (==0.0.18)
Requires-Dist: eth-account (==0.2.3)
Requires-Dist: ipfsapi (==0.4.3)
